{"v":"5.8.1","fr":29.9700012207031,"ip":0,"op":90.0000036657751,"w":1080,"h":1920,"nm":"logo animation","ddd":0,"assets":[],"layers":[{"ddd":0,"ind":1,"ty":4,"nm":"Q Outlines","sr":1,"ks":{"o":{"a":1,"k":[{"i":{"x":[0.833],"y":[0.833]},"o":{"x":[0.167],"y":[0.167]},"t":43,"s":[0]},{"t":45.0000018328876,"s":[100]}],"ix":11},"r":{"a":1,"k":[{"i":{"x":[0.129],"y":[1]},"o":{"x":[0.333],"y":[0]},"t":28,"s":[0]},{"i":{"x":[0.069],"y":[1]},"o":{"x":[0.333],"y":[0]},"t":38,"s":[63]},{"t":47.0000019143492,"s":[0]}],"ix":10},"p":{"a":1,"k":[{"i":{"x":0.009,"y":0.48},"o":{"x":0.842,"y":0},"t":18,"s":[1294.656,1867.896,0],"to":[0,0,0],"ti":[138.051,59.156,0]},{"i":{"x":0.14,"y":0.348},"o":{"x":0.74,"y":0.553},"t":28,"s":[714.051,1571.156,0],"to":[-138.051,-59.156,0],"ti":[45.233,141.877,0]},{"i":{"x":0.228,"y":1},"o":{"x":0.673,"y":0.258},"t":38,"s":[313.689,1475.218,0],"to":[-45.233,-141.877,0],"ti":[0,0,0]},{"t":47.0000019143492,"s":[442.656,719.896,0]}],"ix":2,"l":2},"a":{"a":0,"k":[125.287,122.621,0],"ix":1,"l":2},"s":{"a":1,"k":[{"i":{"x":[0.332,0.332,0.667],"y":[1,1,1]},"o":{"x":[0.333,0.333,0.333],"y":[0,0,0]},"t":18,"s":[23,23,100]},{"t":47.0000019143492,"s":[100,100,100]}],"ix":6,"l":2}},"ao":0,"shapes":[{"ty":"gr","it":[{"ind":0,"ty":"sh","ix":1,"ks":{"a":0,"k":{"i":[[27.774,16.599],[-0.335,-48.608],[-32.505,47]],"o":[[-41.171,-24.605],[0.398,57.943],[17.892,-25.87]],"v":[[38.036,-53.426],[-54.558,-2.216],[53.88,31.855]],"c":true},"ix":2},"nm":"Path 1","mn":"ADBE Vector Shape - Group","hd":false},{"ind":1,"ty":"sh","ix":2,"ks":{"a":0,"k":{"i":[[0.629,0.739],[-87.306,-36.823],[31.248,-46.211],[0,0],[16.57,13.539],[0,0],[28.221,30.655]],"o":[[-63.596,-74.632],[52.027,21.943],[0,0],[12.231,17.85],[0,0],[-35.138,21.919],[-0.76,-0.825]],"v":[[-61.441,56.291],[40.878,-85.548],[78.594,48.106],[112.806,84.755],[86.676,108.832],[52.331,73.686],[-60.101,59.521]],"c":true},"ix":2},"nm":"Path 2","mn":"ADBE Vector Shape - Group","hd":false},{"ty":"mm","mm":1,"nm":"Merge Paths 1","mn":"ADBE Vector Filter - Merge","hd":false},{"ty":"fl","c":{"a":0,"k":[0.074509803922,0.258823529412,0.458823559331,1],"ix":4},"o":{"a":0,"k":100,"ix":5},"r":1,"bm":0,"nm":"Fill 1","mn":"ADBE Vector Graphic - Fill","hd":false},{"ty":"tr","p":{"a":0,"k":[125.287,122.621],"ix":2},"a":{"a":0,"k":[0,0],"ix":1},"s":{"a":0,"k":[100,100],"ix":3},"r":{"a":0,"k":0,"ix":6},"o":{"a":0,"k":100,"ix":7},"sk":{"a":0,"k":0,"ix":4},"sa":{"a":0,"k":0,"ix":5},"nm":"Transform"}],"nm":"Group 1","np":4,"cix":2,"bm":0,"ix":1,"mn":"ADBE Vector Group","hd":false}],"ip":18.000000733155,"op":917.000037350176,"st":18.000000733155,"bm":0},{"ddd":0,"ind":2,"ty":3,"nm":"Q","sr":1,"ks":{"o":{"a":1,"k":[{"i":{"x":[0.833],"y":[0.833]},"o":{"x":[0.167],"y":[0.167]},"t":43,"s":[0]},{"t":45.0000018328876,"s":[100]}],"ix":11},"r":{"a":1,"k":[{"i":{"x":[0.129],"y":[1]},"o":{"x":[0.333],"y":[0]},"t":28,"s":[0]},{"i":{"x":[0.069],"y":[1]},"o":{"x":[0.333],"y":[0]},"t":38,"s":[63]},{"t":47.0000019143492,"s":[0]}],"ix":10},"p":{"a":1,"k":[{"i":{"x":0.009,"y":0.48},"o":{"x":0.842,"y":0},"t":18,"s":[1294.656,1867.896,0],"to":[0,0,0],"ti":[138.051,59.156,0]},{"i":{"x":0.14,"y":0.348},"o":{"x":0.74,"y":0.553},"t":28,"s":[714.051,1571.156,0],"to":[-138.051,-59.156,0],"ti":[45.233,141.877,0]},{"i":{"x":0.228,"y":1},"o":{"x":0.673,"y":0.258},"t":38,"s":[313.689,1475.218,0],"to":[-45.233,-141.877,0],"ti":[0,0,0]},{"t":47.0000019143492,"s":[442.656,719.896,0]}],"ix":2,"l":2},"a":{"a":0,"k":[125.287,122.621,0],"ix":1,"l":2},"s":{"a":1,"k":[{"i":{"x":[0.332,0.332,0.667],"y":[1,1,1]},"o":{"x":[0.333,0.333,0.333],"y":[0,0,0]},"t":18,"s":[23,23,100]},{"t":47.0000019143492,"s":[100,100,100]}],"ix":6,"l":2}},"ao":0,"ip":18.000000733155,"op":917.000037350176,"st":18.000000733155,"bm":0},{"ddd":0,"ind":3,"ty":4,"nm":"Reflect Outlines","parent":2,"sr":1,"ks":{"o":{"a":1,"k":[{"i":{"x":[0.833],"y":[0.833]},"o":{"x":[0.167],"y":[0.167]},"t":43,"s":[0]},{"t":45.0000018328876,"s":[100]}],"ix":11},"r":{"a":0,"k":0,"ix":10},"p":{"a":0,"k":[107.178,99.275,0],"ix":2,"l":2},"a":{"a":0,"k":[35.261,36.429,0],"ix":1,"l":2},"s":{"a":0,"k":[100,100,100],"ix":6,"l":2}},"ao":0,"shapes":[{"ty":"gr","it":[{"ind":0,"ty":"sh","ix":1,"ks":{"a":0,"k":{"i":[[-38.191,-8.74],[0,0],[7.104,-16.623],[0,0]],"o":[[0,0],[-16.08,8.574],[0,0],[-11.531,-37.046]],"v":[[35.011,-27.439],[16.233,-19.029],[-17.833,19.78],[-23.48,36.179]],"c":true},"ix":2},"nm":"Path 1","mn":"ADBE Vector Shape - Group","hd":false},{"ty":"fl","c":{"a":0,"k":[0.980392216701,0.643137254902,0.101960791794,1],"ix":4},"o":{"a":0,"k":100,"ix":5},"r":1,"bm":0,"nm":"Fill 1","mn":"ADBE Vector Graphic - Fill","hd":false},{"ty":"tr","p":{"a":0,"k":[35.261,36.429],"ix":2},"a":{"a":0,"k":[0,0],"ix":1},"s":{"a":0,"k":[100,100],"ix":3},"r":{"a":0,"k":0,"ix":6},"o":{"a":0,"k":100,"ix":7},"sk":{"a":0,"k":0,"ix":4},"sa":{"a":0,"k":0,"ix":5},"nm":"Transform"}],"nm":"Group 1","np":2,"cix":2,"bm":0,"ix":1,"mn":"ADBE Vector Group","hd":false}],"ip":16.0000006516934,"op":915.000037268714,"st":16.0000006516934,"bm":0},{"ddd":0,"ind":5,"ty":4,"nm":"u Outlines","sr":1,"ks":{"o":{"a":1,"k":[{"i":{"x":[0.833],"y":[0.833]},"o":{"x":[0.167],"y":[0.167]},"t":21,"s":[0]},{"t":24.00000097754,"s":[100]}],"ix":11},"r":{"a":0,"k":0,"ix":10},"p":{"a":1,"k":[{"i":{"x":0,"y":1},"o":{"x":0.395,"y":0},"t":16,"s":[-395.721,762.48,0],"to":[0,0,0],"ti":[0,0,0]},{"t":31.0000012626559,"s":[612.279,762.48,0]}],"ix":2,"l":2},"a":{"a":0,"k":[56.465,53.823,0],"ix":1,"l":2},"s":{"a":0,"k":[100,100,100],"ix":6,"l":2}},"ao":0,"ef":[{"ty":5,"nm":"Elastic Controller","np":5,"mn":"Pseudo/MDS Elastic Controller","ix":1,"en":1,"ef":[{"ty":0,"nm":"Amplitude","mn":"Pseudo/MDS Elastic Controller-0001","ix":1,"v":{"a":0,"k":27,"ix":1}},{"ty":0,"nm":"Frequency","mn":"Pseudo/MDS Elastic Controller-0002","ix":2,"v":{"a":0,"k":148,"ix":2}},{"ty":0,"nm":"Decay","mn":"Pseudo/MDS Elastic Controller-0003","ix":3,"v":{"a":0,"k":37,"ix":3}}]}],"shapes":[{"ty":"gr","it":[{"ind":0,"ty":"sh","ix":1,"ks":{"a":0,"k":{"i":[[3.493,-23.387],[0,0],[0,0],[8.293,-2.473],[2.831,21.569],[-1.357,24.033],[0,0],[0,0],[-12.255,1.206],[-2.014,11.76],[0,0],[-2.974,1.74],[0,0],[0.174,-1.645],[0.97,-6.477]],"o":[[0,0],[0,0],[-6.618,5.206],[-18.763,5.594],[-3.145,-23.96],[0,0],[0,0],[2.525,11.756],[13.687,-1.345],[0,0],[1.958,-3.983],[0,0],[2.114,0],[-0.69,6.528],[-3.506,23.398]],"v":[[41.272,47.236],[12.533,47.236],[13.548,34.92],[-7.767,47.98],[-53.071,24.056],[-44.947,-51.298],[-14.155,-51.298],[-22.289,8.649],[-2.297,23.676],[18.429,-3.832],[25.012,-49.59],[33.573,-52.324],[54.101,-52.324],[55.527,-43.704],[51.632,-22.975]],"c":true},"ix":2},"nm":"Path 1","mn":"ADBE Vector Shape - Group","hd":false},{"ty":"fl","c":{"a":0,"k":[0.980392216701,0.643137254902,0.101960791794,1],"ix":4},"o":{"a":0,"k":100,"ix":5},"r":1,"bm":0,"nm":"Fill 1","mn":"ADBE Vector Graphic - Fill","hd":false},{"ty":"tr","p":{"a":0,"k":[56.465,53.824],"ix":2},"a":{"a":0,"k":[0,0],"ix":1},"s":{"a":0,"k":[100,100],"ix":3},"r":{"a":0,"k":0,"ix":6},"o":{"a":0,"k":100,"ix":7},"sk":{"a":0,"k":0,"ix":4},"sa":{"a":0,"k":0,"ix":5},"nm":"Transform"}],"nm":"Group 1","np":2,"cix":2,"bm":0,"ix":1,"mn":"ADBE Vector Group","hd":false}],"ip":16.0000006516934,"op":915.000037268714,"st":16.0000006516934,"bm":0},{"ddd":0,"ind":7,"ty":4,"nm":"i Outlines","sr":1,"ks":{"o":{"a":1,"k":[{"i":{"x":[0.833],"y":[0.833]},"o":{"x":[0.167],"y":[0.167]},"t":21,"s":[0]},{"t":24.00000097754,"s":[100]}],"ix":11},"r":{"a":0,"k":0,"ix":10},"p":{"a":1,"k":[{"i":{"x":0,"y":1},"o":{"x":0.395,"y":0},"t":16,"s":[-306.965,739.23,0],"to":[0,0,0],"ti":[0,0,0]},{"t":31.0000012626559,"s":[701.035,739.23,0]}],"ix":2,"l":2},"a":{"a":0,"k":[26.18,70.737,0],"ix":1,"l":2},"s":{"a":0,"k":[100,100,100],"ix":6,"l":2}},"ao":0,"ef":[{"ty":5,"nm":"Elastic Controller","np":5,"mn":"Pseudo/MDS Elastic Controller","ix":1,"en":1,"ef":[{"ty":0,"nm":"Amplitude","mn":"Pseudo/MDS Elastic Controller-0001","ix":1,"v":{"a":0,"k":27,"ix":1}},{"ty":0,"nm":"Frequency","mn":"Pseudo/MDS Elastic Controller-0002","ix":2,"v":{"a":0,"k":148,"ix":2}},{"ty":0,"nm":"Decay","mn":"Pseudo/MDS Elastic Controller-0003","ix":3,"v":{"a":0,"k":37,"ix":3}}]}],"shapes":[{"ty":"gr","it":[{"ind":0,"ty":"sh","ix":1,"ks":{"a":0,"k":{"i":[[0,-9.839],[9.839,0],[0,9.839],[-9.839,0]],"o":[[0,9.839],[-9.839,0],[0,-9.839],[9.839,0]],"v":[[17.815,0],[0,17.815],[-17.815,0],[0,-17.815]],"c":true},"ix":2},"nm":"Path 1","mn":"ADBE Vector Shape - Group","hd":false},{"ty":"fl","c":{"a":0,"k":[0.980392216701,0.643137254902,0.101960791794,1],"ix":4},"o":{"a":0,"k":100,"ix":5},"r":1,"bm":0,"nm":"Fill 1","mn":"ADBE Vector Graphic - Fill","hd":false},{"ty":"tr","p":{"a":0,"k":[34.295,18.065],"ix":2},"a":{"a":0,"k":[0,0],"ix":1},"s":{"a":0,"k":[100,100],"ix":3},"r":{"a":0,"k":0,"ix":6},"o":{"a":0,"k":100,"ix":7},"sk":{"a":0,"k":0,"ix":4},"sa":{"a":0,"k":0,"ix":5},"nm":"Transform"}],"nm":"Group 1","np":2,"cix":2,"bm":0,"ix":1,"mn":"ADBE Vector Group","hd":false},{"ty":"gr","it":[{"ind":0,"ty":"sh","ix":1,"ks":{"a":0,"k":{"i":[[0,0],[0,0],[0,0],[0,0]],"o":[[0,0],[0,0],[0,0],[0,0]],"v":[[23.094,-49.268],[7.185,49.268],[-23.094,49.268],[-7.698,-49.268]],"c":true},"ix":2},"nm":"Path 1","mn":"ADBE Vector Shape - Group","hd":false},{"ty":"fl","c":{"a":0,"k":[0.980392216701,0.643137254902,0.101960791794,1],"ix":4},"o":{"a":0,"k":100,"ix":5},"r":1,"bm":0,"nm":"Fill 1","mn":"ADBE Vector Graphic - Fill","hd":false},{"ty":"tr","p":{"a":0,"k":[23.344,91.957],"ix":2},"a":{"a":0,"k":[0,0],"ix":1},"s":{"a":0,"k":[100,100],"ix":3},"r":{"a":0,"k":0,"ix":6},"o":{"a":0,"k":100,"ix":7},"sk":{"a":0,"k":0,"ix":4},"sa":{"a":0,"k":0,"ix":5},"nm":"Transform"}],"nm":"Group 2","np":2,"cix":2,"bm":0,"ix":2,"mn":"ADBE Vector Group","hd":false}],"ip":16.0000006516934,"op":915.000037268714,"st":16.0000006516934,"bm":0},{"ddd":0,"ind":9,"ty":4,"nm":"c Outlines","sr":1,"ks":{"o":{"a":1,"k":[{"i":{"x":[0.833],"y":[0.833]},"o":{"x":[0.167],"y":[0.167]},"t":21,"s":[0]},{"t":24.00000097754,"s":[100]}],"ix":11},"r":{"a":0,"k":0,"ix":10},"p":{"a":1,"k":[{"i":{"x":0,"y":1},"o":{"x":0.395,"y":0},"t":16,"s":[-238.428,760.631,0],"to":[0,0,0],"ti":[0,0,0]},{"t":31.0000012626559,"s":[769.572,760.631,0]}],"ix":2,"l":2},"a":{"a":0,"k":[62.278,52.205,0],"ix":1,"l":2},"s":{"a":0,"k":[100,100,100],"ix":6,"l":2}},"ao":0,"ef":[{"ty":5,"nm":"Elastic Controller","np":5,"mn":"Pseudo/MDS Elastic Controller","ix":1,"en":1,"ef":[{"ty":0,"nm":"Amplitude","mn":"Pseudo/MDS Elastic Controller-0001","ix":1,"v":{"a":0,"k":27,"ix":1}},{"ty":0,"nm":"Frequency","mn":"Pseudo/MDS Elastic Controller-0002","ix":2,"v":{"a":0,"k":148,"ix":2}},{"ty":0,"nm":"Decay","mn":"Pseudo/MDS Elastic Controller-0003","ix":3,"v":{"a":0,"k":37,"ix":3}}]},{"ty":5,"nm":"Elastic Controller 2","np":5,"mn":"Pseudo/MDS Elastic Controller","ix":2,"en":1,"ef":[{"ty":0,"nm":"Amplitude","mn":"Pseudo/MDS Elastic Controller-0001","ix":1,"v":{"a":0,"k":27,"ix":1}},{"ty":0,"nm":"Frequency","mn":"Pseudo/MDS Elastic Controller-0002","ix":2,"v":{"a":0,"k":148,"ix":2}},{"ty":0,"nm":"Decay","mn":"Pseudo/MDS Elastic Controller-0003","ix":3,"v":{"a":0,"k":37,"ix":3}}]}],"shapes":[{"ty":"gr","it":[{"ind":0,"ty":"sh","ix":1,"ks":{"a":0,"k":{"i":[[-1.288,-6.89],[1.546,0.741],[2.992,-21.546],[-20.012,11.586],[1.031,-0.783],[10.067,0.832],[-69.369,4.879],[-1.107,-6.84]],"o":[[-0.673,0.812],[-17.172,-8.232],[-4.514,32.5],[-0.545,3.287],[-8.187,6.212],[-68.678,-5.672],[5.836,-0.411],[0.873,5.387]],"v":[[56.409,-15.583],[46.369,-21.441],[-3.028,-1.631],[50.245,18.294],[47.566,44.059],[6.65,51.122],[23.014,-51.544],[61.155,-43.85]],"c":true},"ix":2},"nm":"Path 1","mn":"ADBE Vector Shape - Group","hd":false},{"ty":"fl","c":{"a":0,"k":[0.980392216701,0.643137254902,0.101960791794,1],"ix":4},"o":{"a":0,"k":100,"ix":5},"r":1,"bm":0,"nm":"Fill 1","mn":"ADBE Vector Graphic - Fill","hd":false},{"ty":"tr","p":{"a":0,"k":[62.278,52.205],"ix":2},"a":{"a":0,"k":[0,0],"ix":1},"s":{"a":0,"k":[100,100],"ix":3},"r":{"a":0,"k":0,"ix":6},"o":{"a":0,"k":100,"ix":7},"sk":{"a":0,"k":0,"ix":4},"sa":{"a":0,"k":0,"ix":5},"nm":"Transform"}],"nm":"Group 1","np":2,"cix":2,"bm":0,"ix":1,"mn":"ADBE Vector Group","hd":false}],"ip":16.0000006516934,"op":915.000037268714,"st":16.0000006516934,"bm":0},{"ddd":0,"ind":11,"ty":4,"nm":"k Outlines","sr":1,"ks":{"o":{"a":1,"k":[{"i":{"x":[0.833],"y":[0.833]},"o":{"x":[0.167],"y":[0.167]},"t":21,"s":[0]},{"t":24.00000097754,"s":[100]}],"ix":11},"r":{"a":0,"k":0,"ix":10},"p":{"a":1,"k":[{"i":{"x":0,"y":1},"o":{"x":0.395,"y":0},"t":16,"s":[-114.271,739.921,0],"to":[0,0,0],"ti":[0,0,0]},{"t":31.0000012626559,"s":[893.729,739.921,0]}],"ix":2,"l":2},"a":{"a":0,"k":[58.755,70.046,0],"ix":1,"l":2},"s":{"a":0,"k":[100,100,100],"ix":6,"l":2}},"ao":0,"ef":[{"ty":5,"nm":"Elastic Controller","np":5,"mn":"Pseudo/MDS Elastic Controller","ix":1,"en":1,"ef":[{"ty":0,"nm":"Amplitude","mn":"Pseudo/MDS Elastic Controller-0001","ix":1,"v":{"a":0,"k":27,"ix":1}},{"ty":0,"nm":"Frequency","mn":"Pseudo/MDS Elastic Controller-0002","ix":2,"v":{"a":0,"k":148,"ix":2}},{"ty":0,"nm":"Decay","mn":"Pseudo/MDS Elastic Controller-0003","ix":3,"v":{"a":0,"k":37,"ix":3}}]},{"ty":5,"nm":"Elastic Controller 2","np":5,"mn":"Pseudo/MDS Elastic Controller","ix":2,"en":1,"ef":[{"ty":0,"nm":"Amplitude","mn":"Pseudo/MDS Elastic Controller-0001","ix":1,"v":{"a":0,"k":27,"ix":1}},{"ty":0,"nm":"Frequency","mn":"Pseudo/MDS Elastic Controller-0002","ix":2,"v":{"a":0,"k":148,"ix":2}},{"ty":0,"nm":"Decay","mn":"Pseudo/MDS Elastic Controller-0003","ix":3,"v":{"a":0,"k":37,"ix":3}}]}],"shapes":[{"ty":"gr","it":[{"ind":0,"ty":"sh","ix":1,"ks":{"a":0,"k":{"i":[[0,0],[0,0],[-1.029,0.791],[-2.722,0],[0,0],[0,0],[0,0],[0,0],[0,0],[3.599,-3.842],[2.596,-7.54],[0,0],[0,0]],"o":[[0,0],[1.779,0.463],[6.133,-4.711],[0,0],[0,0],[0,0],[0,0],[0,0],[-4.133,3.837],[-5.406,5.771],[0,0],[0,0],[0,0]],"v":[[-7.185,-69.796],[-19.497,11.286],[-16.416,9.758],[22.068,-28.739],[58.505,-28.739],[15.682,11.79],[46.188,69.785],[10.477,69.574],[-7.714,31.821],[-22.617,43.587],[-28.74,69.796],[-58.505,69.796],[-36.438,-69.796]],"c":true},"ix":2},"nm":"Path 1","mn":"ADBE Vector Shape - Group","hd":false},{"ty":"fl","c":{"a":0,"k":[0.980392216701,0.643137254902,0.101960791794,1],"ix":4},"o":{"a":0,"k":100,"ix":5},"r":1,"bm":0,"nm":"Fill 1","mn":"ADBE Vector Graphic - Fill","hd":false},{"ty":"tr","p":{"a":0,"k":[58.755,70.046],"ix":2},"a":{"a":0,"k":[0,0],"ix":1},"s":{"a":0,"k":[100,100],"ix":3},"r":{"a":0,"k":0,"ix":6},"o":{"a":0,"k":100,"ix":7},"sk":{"a":0,"k":0,"ix":4},"sa":{"a":0,"k":0,"ix":5},"nm":"Transform"}],"nm":"Group 1","np":2,"cix":2,"bm":0,"ix":1,"mn":"ADBE Vector Group","hd":false}],"ip":16.0000006516934,"op":915.000037268714,"st":16.0000006516934,"bm":0},{"ddd":0,"ind":13,"ty":4,"nm":"s Outlines","sr":1,"ks":{"o":{"a":1,"k":[{"i":{"x":[0.833],"y":[0.833]},"o":{"x":[0.167],"y":[0.167]},"t":24,"s":[0]},{"t":27.0000010997325,"s":[100]}],"ix":11},"r":{"a":0,"k":0,"ix":10},"p":{"a":1,"k":[{"i":{"x":0,"y":1},"o":{"x":0.395,"y":0},"t":20,"s":[-501.385,922.959,0],"to":[0,0,0],"ti":[0,0,0]},{"t":35.0000014255792,"s":[506.615,922.959,0]}],"ix":2,"l":2},"a":{"a":0,"k":[55.627,66.169,0],"ix":1,"l":2},"s":{"a":0,"k":[100,100,100],"ix":6,"l":2}},"ao":0,"ef":[{"ty":5,"nm":"Elastic Controller","np":5,"mn":"Pseudo/MDS Elastic Controller","ix":1,"en":1,"ef":[{"ty":0,"nm":"Amplitude","mn":"Pseudo/MDS Elastic Controller-0001","ix":1,"v":{"a":0,"k":27,"ix":1}},{"ty":0,"nm":"Frequency","mn":"Pseudo/MDS Elastic Controller-0002","ix":2,"v":{"a":0,"k":148,"ix":2}},{"ty":0,"nm":"Decay","mn":"Pseudo/MDS Elastic Controller-0003","ix":3,"v":{"a":0,"k":37,"ix":3}}]},{"ty":5,"nm":"Elastic Controller 2","np":5,"mn":"Pseudo/MDS Elastic Controller","ix":2,"en":1,"ef":[{"ty":0,"nm":"Amplitude","mn":"Pseudo/MDS Elastic Controller-0001","ix":1,"v":{"a":0,"k":27,"ix":1}},{"ty":0,"nm":"Frequency","mn":"Pseudo/MDS Elastic Controller-0002","ix":2,"v":{"a":0,"k":148,"ix":2}},{"ty":0,"nm":"Decay","mn":"Pseudo/MDS Elastic Controller-0003","ix":3,"v":{"a":0,"k":37,"ix":3}}]}],"shapes":[{"ty":"gr","it":[{"ind":0,"ty":"sh","ix":1,"ks":{"a":0,"k":{"i":[[-27.434,-15.346],[1.719,-7.19],[4.479,1.191],[11.057,-1.89],[-10.78,-6.002],[-3.143,-23.037],[33.317,3.907],[3.217,3.633],[-0.425,3.474],[-0.232,6.665],[-2.036,-0.874],[-9.146,8.287],[6.152,2.554],[-4.342,33.747]],"o":[[-1.973,7.262],[-1.284,5.366],[-10.706,-2.846],[-10.208,1.746],[15.535,8.65],[6.04,44.266],[-5.219,-0.612],[-2.708,-3.058],[0.809,-6.615],[0.81,-0.948],[10.694,4.588],[6.863,-6.219],[-21.695,-9.005],[5.163,-40.113]],"v":[[52.49,-50.573],[49.373,-27.593],[33.225,-29.811],[-0.923,-32.725],[-5.67,-17.603],[49.337,14.635],[-24.727,62.012],[-52.669,51.958],[-52.31,42.131],[-50.129,22.248],[-35.434,29.611],[13.187,32.186],[7.319,17.648],[-43.714,-25.222]],"c":true},"ix":2},"nm":"Path 1","mn":"ADBE Vector Shape - Group","hd":false},{"ty":"fl","c":{"a":0,"k":[0.980392216701,0.643137254902,0.101960791794,1],"ix":4},"o":{"a":0,"k":100,"ix":5},"r":1,"bm":0,"nm":"Fill 1","mn":"ADBE Vector Graphic - Fill","hd":false},{"ty":"tr","p":{"a":0,"k":[55.627,66.169],"ix":2},"a":{"a":0,"k":[0,0],"ix":1},"s":{"a":0,"k":[100,100],"ix":3},"r":{"a":0,"k":0,"ix":6},"o":{"a":0,"k":100,"ix":7},"sk":{"a":0,"k":0,"ix":4},"sa":{"a":0,"k":0,"ix":5},"nm":"Transform"}],"nm":"Group 1","np":2,"cix":2,"bm":0,"ix":1,"mn":"ADBE Vector Group","hd":false}],"ip":20.0000008146167,"op":919.000037431637,"st":20.0000008146167,"bm":0},{"ddd":0,"ind":15,"ty":4,"nm":"a Outlines","sr":1,"ks":{"o":{"a":1,"k":[{"i":{"x":[0.833],"y":[0.833]},"o":{"x":[0.167],"y":[0.167]},"t":24,"s":[0]},{"t":27.0000010997325,"s":[100]}],"ix":11},"r":{"a":0,"k":0,"ix":10},"p":{"a":1,"k":[{"i":{"x":0,"y":1},"o":{"x":0.395,"y":0},"t":20,"s":[-371.145,925.617,0],"to":[0,0,0],"ti":[0,0,0]},{"t":35.0000014255792,"s":[636.855,925.617,0]}],"ix":2,"l":2},"a":{"a":0,"k":[79.526,77.816,0],"ix":1,"l":2},"s":{"a":0,"k":[100,100,100],"ix":6,"l":2}},"ao":0,"ef":[{"ty":5,"nm":"Elastic Controller","np":5,"mn":"Pseudo/MDS Elastic Controller","ix":1,"en":1,"ef":[{"ty":0,"nm":"Amplitude","mn":"Pseudo/MDS Elastic Controller-0001","ix":1,"v":{"a":0,"k":27,"ix":1}},{"ty":0,"nm":"Frequency","mn":"Pseudo/MDS Elastic Controller-0002","ix":2,"v":{"a":0,"k":148,"ix":2}},{"ty":0,"nm":"Decay","mn":"Pseudo/MDS Elastic Controller-0003","ix":3,"v":{"a":0,"k":37,"ix":3}}]},{"ty":5,"nm":"Elastic Controller 2","np":5,"mn":"Pseudo/MDS Elastic Controller","ix":2,"en":1,"ef":[{"ty":0,"nm":"Amplitude","mn":"Pseudo/MDS Elastic Controller-0001","ix":1,"v":{"a":0,"k":27,"ix":1}},{"ty":0,"nm":"Frequency","mn":"Pseudo/MDS Elastic Controller-0002","ix":2,"v":{"a":0,"k":148,"ix":2}},{"ty":0,"nm":"Decay","mn":"Pseudo/MDS Elastic Controller-0003","ix":3,"v":{"a":0,"k":37,"ix":3}}]}],"shapes":[{"ty":"gr","it":[{"ind":0,"ty":"sh","ix":1,"ks":{"a":0,"k":{"i":[[35.97,-5.297],[-42.146,4.082]],"o":[[-51.305,7.392],[45.791,-4.303]],"v":[[7.668,31.667],[7.226,-33.542]],"c":true},"ix":2},"nm":"Path 1","mn":"ADBE Vector Shape - Group","hd":false},{"ind":1,"ty":"sh","ix":2,"ks":{"a":0,"k":{"i":[[0,0],[0,0],[1.767,1.324],[13.35,-34.867],[-50.093,24.936],[-4.857,2.207],[0,0],[0,0],[0,0]],"o":[[0,0],[-1.988,1.986],[-32.991,-25.377],[-20.521,54.174],[4.854,-2.427],[0,0],[0,0],[0,0],[0,0]],"v":[[48.494,-58.368],[45.405,-45.127],[35.693,-52.189],[-58.754,-15.336],[15.393,52.63],[28.965,44.245],[26.977,57.596],[61.844,57.596],[79.276,-58.368]],"c":true},"ix":2},"nm":"Path 2","mn":"ADBE Vector Shape - Group","hd":false},{"ty":"mm","mm":1,"nm":"Merge Paths 1","mn":"ADBE Vector Filter - Merge","hd":false},{"ty":"fl","c":{"a":0,"k":[0.980392216701,0.643137254902,0.101960791794,1],"ix":4},"o":{"a":0,"k":100,"ix":5},"r":1,"bm":0,"nm":"Fill 1","mn":"ADBE Vector Graphic - Fill","hd":false},{"ty":"tr","p":{"a":0,"k":[79.525,77.816],"ix":2},"a":{"a":0,"k":[0,0],"ix":1},"s":{"a":0,"k":[100,100],"ix":3},"r":{"a":0,"k":0,"ix":6},"o":{"a":0,"k":100,"ix":7},"sk":{"a":0,"k":0,"ix":4},"sa":{"a":0,"k":0,"ix":5},"nm":"Transform"}],"nm":"Group 1","np":4,"cix":2,"bm":0,"ix":1,"mn":"ADBE Vector Group","hd":false}],"ip":20.0000008146167,"op":919.000037431637,"st":20.0000008146167,"bm":0},{"ddd":0,"ind":17,"ty":4,"nm":"l Outlines","sr":1,"ks":{"o":{"a":1,"k":[{"i":{"x":[0.833],"y":[0.833]},"o":{"x":[0.167],"y":[0.167]},"t":24,"s":[0]},{"t":27.0000010997325,"s":[100]}],"ix":11},"r":{"a":0,"k":0,"ix":10},"p":{"a":1,"k":[{"i":{"x":0,"y":1},"o":{"x":0.395,"y":0},"t":20,"s":[-261.047,907.739,0],"to":[0,0,0],"ti":[0,0,0]},{"t":35.0000014255792,"s":[746.953,907.739,0]}],"ix":2,"l":2},"a":{"a":0,"k":[27.963,75.691,0],"ix":1,"l":2},"s":{"a":0,"k":[100,100,100],"ix":6,"l":2}},"ao":0,"ef":[{"ty":5,"nm":"Elastic Controller","np":5,"mn":"Pseudo/MDS Elastic Controller","ix":1,"en":1,"ef":[{"ty":0,"nm":"Amplitude","mn":"Pseudo/MDS Elastic Controller-0001","ix":1,"v":{"a":0,"k":27,"ix":1}},{"ty":0,"nm":"Frequency","mn":"Pseudo/MDS Elastic Controller-0002","ix":2,"v":{"a":0,"k":148,"ix":2}},{"ty":0,"nm":"Decay","mn":"Pseudo/MDS Elastic Controller-0003","ix":3,"v":{"a":0,"k":37,"ix":3}}]},{"ty":5,"nm":"Elastic Controller 2","np":5,"mn":"Pseudo/MDS Elastic Controller","ix":2,"en":1,"ef":[{"ty":0,"nm":"Amplitude","mn":"Pseudo/MDS Elastic Controller-0001","ix":1,"v":{"a":0,"k":27,"ix":1}},{"ty":0,"nm":"Frequency","mn":"Pseudo/MDS Elastic Controller-0002","ix":2,"v":{"a":0,"k":148,"ix":2}},{"ty":0,"nm":"Decay","mn":"Pseudo/MDS Elastic Controller-0003","ix":3,"v":{"a":0,"k":37,"ix":3}}]}],"shapes":[{"ty":"gr","it":[{"ind":0,"ty":"sh","ix":1,"ks":{"a":0,"k":{"i":[[0,0],[0,0],[0,0],[0,0]],"o":[[0,0],[0,0],[0,0],[0,0]],"v":[[27.713,-75.441],[5.132,75.441],[-27.713,75.441],[-4.106,-75.441]],"c":true},"ix":2},"nm":"Path 1","mn":"ADBE Vector Shape - Group","hd":false},{"ty":"fl","c":{"a":0,"k":[0.980392216701,0.643137254902,0.101960791794,1],"ix":4},"o":{"a":0,"k":100,"ix":5},"r":1,"bm":0,"nm":"Fill 1","mn":"ADBE Vector Graphic - Fill","hd":false},{"ty":"tr","p":{"a":0,"k":[27.963,75.691],"ix":2},"a":{"a":0,"k":[0,0],"ix":1},"s":{"a":0,"k":[100,100],"ix":3},"r":{"a":0,"k":0,"ix":6},"o":{"a":0,"k":100,"ix":7},"sk":{"a":0,"k":0,"ix":4},"sa":{"a":0,"k":0,"ix":5},"nm":"Transform"}],"nm":"Group 1","np":2,"cix":2,"bm":0,"ix":1,"mn":"ADBE Vector Group","hd":false}],"ip":20.0000008146167,"op":919.000037431637,"st":20.0000008146167,"bm":0},{"ddd":0,"ind":19,"ty":4,"nm":"e Outlines","sr":1,"ks":{"o":{"a":1,"k":[{"i":{"x":[0.833],"y":[0.833]},"o":{"x":[0.167],"y":[0.167]},"t":24,"s":[0]},{"t":27.0000010997325,"s":[100]}],"ix":11},"r":{"a":0,"k":0,"ix":10},"p":{"a":1,"k":[{"i":{"x":0,"y":1},"o":{"x":0.395,"y":0},"t":20,"s":[-175.684,919.935,0],"to":[0,0,0],"ti":[0,0,0]},{"t":35.0000014255792,"s":[832.316,919.935,0]}],"ix":2,"l":2},"a":{"a":0,"k":[73.181,76.327,0],"ix":1,"l":2},"s":{"a":0,"k":[100,100,100],"ix":6,"l":2}},"ao":0,"ef":[{"ty":5,"nm":"Elastic Controller","np":5,"mn":"Pseudo/MDS Elastic Controller","ix":1,"en":1,"ef":[{"ty":0,"nm":"Amplitude","mn":"Pseudo/MDS Elastic Controller-0001","ix":1,"v":{"a":0,"k":27,"ix":1}},{"ty":0,"nm":"Frequency","mn":"Pseudo/MDS Elastic Controller-0002","ix":2,"v":{"a":0,"k":148,"ix":2}},{"ty":0,"nm":"Decay","mn":"Pseudo/MDS Elastic Controller-0003","ix":3,"v":{"a":0,"k":37,"ix":3}}]},{"ty":5,"nm":"Elastic Controller 2","np":5,"mn":"Pseudo/MDS Elastic Controller","ix":2,"en":1,"ef":[{"ty":0,"nm":"Amplitude","mn":"Pseudo/MDS Elastic Controller-0001","ix":1,"v":{"a":0,"k":27,"ix":1}},{"ty":0,"nm":"Frequency","mn":"Pseudo/MDS Elastic Controller-0002","ix":2,"v":{"a":0,"k":148,"ix":2}},{"ty":0,"nm":"Decay","mn":"Pseudo/MDS Elastic Controller-0003","ix":3,"v":{"a":0,"k":37,"ix":3}}]}],"shapes":[{"ty":"gr","it":[{"ind":0,"ty":"sh","ix":1,"ks":{"a":0,"k":{"i":[[0,0],[0.439,-33.763]],"o":[[5.406,-27.804],[0,0]],"v":[[-18.647,-6.565],[37.846,-6.565]],"c":true},"ix":2},"nm":"Path 1","mn":"ADBE Vector Shape - Group","hd":false},{"ind":1,"ty":"sh","ix":2,"ks":{"a":0,"k":{"i":[[20.411,-61.236],[-53.842,15.447],[-1.325,2.868],[-1.323,5.407],[18.315,10.261],[0.111,8.496],[0,0],[-0.332,4.634]],"o":[[-22.177,66.644],[2.869,-0.773],[1.765,-4.082],[-18.867,6.069],[-7.171,-4.083],[0,0],[0.221,-4.854],[4.304,-77.236]],"v":[[-50.755,-9.434],[40.932,60.63],[50.643,55.996],[52.188,32.494],[-10.482,34.039],[-21.737,16.054],[66.531,16.054],[68.628,1.159]],"c":true},"ix":2},"nm":"Path 2","mn":"ADBE Vector Shape - Group","hd":false},{"ty":"mm","mm":1,"nm":"Merge Paths 1","mn":"ADBE Vector Filter - Merge","hd":false},{"ty":"fl","c":{"a":0,"k":[0.980392216701,0.643137254902,0.101960791794,1],"ix":4},"o":{"a":0,"k":100,"ix":5},"r":1,"bm":0,"nm":"Fill 1","mn":"ADBE Vector Graphic - Fill","hd":false},{"ty":"tr","p":{"a":0,"k":[73.181,76.327],"ix":2},"a":{"a":0,"k":[0,0],"ix":1},"s":{"a":0,"k":[100,100],"ix":3},"r":{"a":0,"k":0,"ix":6},"o":{"a":0,"k":100,"ix":7},"sk":{"a":0,"k":0,"ix":4},"sa":{"a":0,"k":0,"ix":5},"nm":"Transform"}],"nm":"Group 1","np":4,"cix":2,"bm":0,"ix":1,"mn":"ADBE Vector Group","hd":false}],"ip":20.0000008146167,"op":919.000037431637,"st":20.0000008146167,"bm":0},{"ddd":0,"ind":21,"ty":4,"nm":"Speed 1 Outlines","sr":1,"ks":{"o":{"a":1,"k":[{"i":{"x":[0.833],"y":[0.833]},"o":{"x":[0.167],"y":[0.167]},"t":22,"s":[0]},{"t":25.0000010182709,"s":[100]}],"ix":11},"r":{"a":0,"k":0,"ix":10},"p":{"a":1,"k":[{"i":{"x":0,"y":1},"o":{"x":0.395,"y":0},"t":17,"s":[-567.136,1034.748,0],"to":[0,0,0],"ti":[0,0,0]},{"t":32.0000013033867,"s":[440.864,1034.748,0]}],"ix":2,"l":2},"a":{"a":0,"k":[132.108,11.812,0],"ix":1,"l":2},"s":{"a":0,"k":[100,100,100],"ix":6,"l":2}},"ao":0,"ef":[{"ty":5,"nm":"Elastic Controller","np":5,"mn":"Pseudo/MDS Elastic Controller","ix":1,"en":1,"ef":[{"ty":0,"nm":"Amplitude","mn":"Pseudo/MDS Elastic Controller-0001","ix":1,"v":{"a":0,"k":27,"ix":1}},{"ty":0,"nm":"Frequency","mn":"Pseudo/MDS Elastic Controller-0002","ix":2,"v":{"a":0,"k":148,"ix":2}},{"ty":0,"nm":"Decay","mn":"Pseudo/MDS Elastic Controller-0003","ix":3,"v":{"a":0,"k":37,"ix":3}}]},{"ty":5,"nm":"Elastic Controller 2","np":5,"mn":"Pseudo/MDS Elastic Controller","ix":2,"en":1,"ef":[{"ty":0,"nm":"Amplitude","mn":"Pseudo/MDS Elastic Controller-0001","ix":1,"v":{"a":0,"k":27,"ix":1}},{"ty":0,"nm":"Frequency","mn":"Pseudo/MDS Elastic Controller-0002","ix":2,"v":{"a":0,"k":148,"ix":2}},{"ty":0,"nm":"Decay","mn":"Pseudo/MDS Elastic Controller-0003","ix":3,"v":{"a":0,"k":37,"ix":3}}]}],"shapes":[{"ty":"gr","it":[{"ind":0,"ty":"sh","ix":1,"ks":{"a":0,"k":{"i":[[-9.922,3.925],[0,0],[9.762,-5.694],[81.337,1.292]],"o":[[0,0],[11.09,1.978],[-81.336,1.298],[-9.173,-5.273]],"v":[[-121.193,-11.323],[118.792,-11.562],[122.096,10.264],[-122.686,10.266]],"c":true},"ix":2},"nm":"Path 1","mn":"ADBE Vector Shape - Group","hd":false},{"ty":"fl","c":{"a":0,"k":[0.980392216701,0.643137254902,0.101960791794,1],"ix":4},"o":{"a":0,"k":100,"ix":5},"r":1,"bm":0,"nm":"Fill 1","mn":"ADBE Vector Graphic - Fill","hd":false},{"ty":"tr","p":{"a":0,"k":[132.108,11.812],"ix":2},"a":{"a":0,"k":[0,0],"ix":1},"s":{"a":0,"k":[100,100],"ix":3},"r":{"a":0,"k":0,"ix":6},"o":{"a":0,"k":100,"ix":7},"sk":{"a":0,"k":0,"ix":4},"sa":{"a":0,"k":0,"ix":5},"nm":"Transform"}],"nm":"Group 1","np":2,"cix":2,"bm":0,"ix":1,"mn":"ADBE Vector Group","hd":false}],"ip":17.0000006924242,"op":916.000037309445,"st":17.0000006924242,"bm":0},{"ddd":0,"ind":23,"ty":4,"nm":"Speed 2 Outlines","sr":1,"ks":{"o":{"a":1,"k":[{"i":{"x":[0.833],"y":[0.833]},"o":{"x":[0.167],"y":[0.167]},"t":18,"s":[0]},{"t":21.0000008553475,"s":[100]}],"ix":11},"r":{"a":0,"k":0,"ix":10},"p":{"a":1,"k":[{"i":{"x":0,"y":1},"o":{"x":0.395,"y":0},"t":13,"s":[-516.932,1074.361,0],"to":[0,0,0],"ti":[0,0,0]},{"t":28.0000011404634,"s":[491.068,1074.361,0]}],"ix":2,"l":2},"a":{"a":0,"k":[143.932,12.417,0],"ix":1,"l":2},"s":{"a":0,"k":[100,100,100],"ix":6,"l":2}},"ao":0,"ef":[{"ty":5,"nm":"Elastic Controller","np":5,"mn":"Pseudo/MDS Elastic Controller","ix":1,"en":1,"ef":[{"ty":0,"nm":"Amplitude","mn":"Pseudo/MDS Elastic Controller-0001","ix":1,"v":{"a":0,"k":27,"ix":1}},{"ty":0,"nm":"Frequency","mn":"Pseudo/MDS Elastic Controller-0002","ix":2,"v":{"a":0,"k":148,"ix":2}},{"ty":0,"nm":"Decay","mn":"Pseudo/MDS Elastic Controller-0003","ix":3,"v":{"a":0,"k":37,"ix":3}}]},{"ty":5,"nm":"Elastic Controller 2","np":5,"mn":"Pseudo/MDS Elastic Controller","ix":2,"en":1,"ef":[{"ty":0,"nm":"Amplitude","mn":"Pseudo/MDS Elastic Controller-0001","ix":1,"v":{"a":0,"k":27,"ix":1}},{"ty":0,"nm":"Frequency","mn":"Pseudo/MDS Elastic Controller-0002","ix":2,"v":{"a":0,"k":148,"ix":2}},{"ty":0,"nm":"Decay","mn":"Pseudo/MDS Elastic Controller-0003","ix":3,"v":{"a":0,"k":37,"ix":3}}]}],"shapes":[{"ty":"gr","it":[{"ind":0,"ty":"sh","ix":1,"ks":{"a":0,"k":{"i":[[-12.335,2.484],[0,0],[11.135,-4.583],[86.663,-0.532]],"o":[[0,0],[10.805,2.535],[-86.547,1.607],[-13.948,1.699]],"v":[[-131.347,-11.912],[130.168,-12.167],[132.547,9.751],[-127.514,10.468]],"c":true},"ix":2},"nm":"Path 1","mn":"ADBE Vector Shape - Group","hd":false},{"ty":"fl","c":{"a":0,"k":[0.980392216701,0.643137254902,0.101960791794,1],"ix":4},"o":{"a":0,"k":100,"ix":5},"r":1,"bm":0,"nm":"Fill 1","mn":"ADBE Vector Graphic - Fill","hd":false},{"ty":"tr","p":{"a":0,"k":[143.932,12.417],"ix":2},"a":{"a":0,"k":[0,0],"ix":1},"s":{"a":0,"k":[100,100],"ix":3},"r":{"a":0,"k":0,"ix":6},"o":{"a":0,"k":100,"ix":7},"sk":{"a":0,"k":0,"ix":4},"sa":{"a":0,"k":0,"ix":5},"nm":"Transform"}],"nm":"Group 1","np":2,"cix":2,"bm":0,"ix":1,"mn":"ADBE Vector Group","hd":false}],"ip":13.0000005295009,"op":912.000037146522,"st":13.0000005295009,"bm":0},{"ddd":0,"ind":25,"ty":4,"nm":"Cart Outlines","sr":1,"ks":{"o":{"a":1,"k":[{"i":{"x":[0.833],"y":[0.833]},"o":{"x":[0.167],"y":[0.167]},"t":14,"s":[0]},{"t":17.0000006924242,"s":[100]}],"ix":11},"r":{"a":0,"k":0,"ix":10},"p":{"a":1,"k":[{"i":{"x":0,"y":1},"o":{"x":0.395,"y":0},"t":6,"s":[-538.684,900.947,0],"to":[0,0,0],"ti":[0,0,0]},{"t":21.0000008553475,"s":[469.316,900.947,0]}],"ix":2,"l":2},"a":{"a":0,"k":[344.082,249.829,0],"ix":1,"l":2},"s":{"a":0,"k":[100,100,100],"ix":6,"l":2}},"ao":0,"ef":[{"ty":5,"nm":"Elastic Controller","np":5,"mn":"Pseudo/MDS Elastic Controller","ix":1,"en":1,"ef":[{"ty":0,"nm":"Amplitude","mn":"Pseudo/MDS Elastic Controller-0001","ix":1,"v":{"a":0,"k":27,"ix":1}},{"ty":0,"nm":"Frequency","mn":"Pseudo/MDS Elastic Controller-0002","ix":2,"v":{"a":0,"k":148,"ix":2}},{"ty":0,"nm":"Decay","mn":"Pseudo/MDS Elastic Controller-0003","ix":3,"v":{"a":0,"k":37,"ix":3}}]}],"shapes":[{"ty":"gr","it":[{"ind":0,"ty":"sh","ix":1,"ks":{"a":1,"k":[{"i":{"x":0,"y":1},"o":{"x":0.333,"y":0},"t":9,"s":[{"i":[[-8.881,8.878],[0.888,-22.878],[3.88,-9.884],[41.844,-3.829],[0,0],[-4.436,52.423],[10.347,55.224],[-1.644,32.858],[0.764,3.306],[0.89,0.81],[8.731,0.747],[25.829,3.311],[-2.635,19.018],[-6.876,2.584],[-13.226,-1.114],[-23.849,-43.415],[1.806,-19.512],[12.25,-100.798],[-25.398,-0.64],[0,0],[-9.197,21.173]],"o":[[16.419,-16.413],[-0.333,8.568],[-15.307,39.006],[0,0],[-52.752,-5.84],[10.313,-67.1],[-6.191,-33.043],[0.17,-3.412],[-0.332,-1.439],[-6.718,-6.121],[-26.136,-2.238],[-17.358,-2.224],[1.014,-7.32],[10.351,-3.891],[44.417,3.739],[9.46,17.223],[-9.346,100.968],[0.288,24.491],[0,0],[22.144,-1.668],[5.871,-13.516]],"v":[[300.585,109.285],[342.943,129.8],[325.619,184.1],[235.085,249.579],[-159.138,249.577],[-240.566,147.542],[-282.051,-47.172],[-299.574,-161.218],[-300.004,-172.057],[-306.81,-183.727],[-337.038,-191.477],[-417.074,-196.632],[-444.196,-227.837],[-428.874,-246.385],[-367.824,-244.855],[-264.488,-199.362],[-254.528,-150.046],[-194.122,154.768],[-152.98,199.283],[227.906,199.293],[279.158,167.405]],"c":true}]},{"t":21.0000008553475,"s":[{"i":[[-8.881,8.878],[0.888,-22.878],[3.88,-9.884],[41.844,-3.829],[0,0],[-4.436,52.423],[-9.097,67.291],[-1.644,32.858],[0.764,3.306],[0.89,0.81],[8.731,0.747],[25.829,3.311],[-2.635,19.018],[-6.876,2.584],[-13.226,-1.114],[-23.849,-43.415],[1.806,-19.512],[12.25,-100.798],[-25.398,-0.64],[0,0],[-9.197,21.173]],"o":[[16.419,-16.413],[-0.333,8.568],[-15.307,39.006],[0,0],[-52.752,-5.84],[10.313,-67.1],[4.504,-33.315],[0.17,-3.412],[-0.332,-1.439],[-6.718,-6.121],[-26.136,-2.238],[-17.358,-2.224],[1.014,-7.32],[10.351,-3.891],[44.417,3.739],[9.46,17.223],[-9.346,100.968],[0.288,24.491],[0,0],[22.144,-1.668],[5.871,-13.516]],"v":[[300.585,109.285],[342.943,129.799],[325.619,184.1],[235.085,249.579],[-159.138,249.577],[-240.566,147.542],[-210.051,-53.913],[-196.574,-160.522],[-197.004,-171.361],[-203.81,-183.03],[-234.038,-190.78],[-314.074,-195.936],[-341.196,-227.14],[-325.874,-245.689],[-264.824,-244.158],[-161.488,-198.665],[-151.528,-149.35],[-194.122,154.768],[-152.98,199.283],[227.906,199.293],[279.158,167.405]],"c":true}]}],"ix":2},"nm":"Path 1","mn":"ADBE Vector Shape - Group","hd":false},{"ty":"fl","c":{"a":0,"k":[0.074509803922,0.258823529412,0.458823529412,1],"ix":4},"o":{"a":0,"k":100,"ix":5},"r":1,"bm":0,"nm":"Fill 1","mn":"ADBE Vector Graphic - Fill","hd":false},{"ty":"tr","p":{"a":0,"k":[344.081,249.829],"ix":2},"a":{"a":0,"k":[0,0],"ix":1},"s":{"a":0,"k":[100,100],"ix":3},"r":{"a":0,"k":0,"ix":6},"o":{"a":0,"k":100,"ix":7},"sk":{"a":0,"k":0,"ix":4},"sa":{"a":0,"k":0,"ix":5},"nm":"Transform"}],"nm":"Group 1","np":2,"cix":2,"bm":0,"ix":1,"mn":"ADBE Vector Group","hd":false}],"ip":6.00000024438501,"op":905.000036861406,"st":6.00000024438501,"bm":0},{"ddd":0,"ind":26,"ty":4,"nm":"Cart Outlines","sr":1,"ks":{"o":{"a":1,"k":[{"i":{"x":[0.833],"y":[0.833]},"o":{"x":[0.167],"y":[0.167]},"t":14,"s":[0]},{"t":17.0000006924242,"s":[100]}],"ix":11},"r":{"a":0,"k":0,"ix":10},"p":{"a":1,"k":[{"i":{"x":0,"y":1},"o":{"x":0.395,"y":0},"t":6,"s":[-538.684,900.947,0],"to":[0,0,0],"ti":[0,0,0]},{"t":21.0000008553475,"s":[469.316,900.947,0]}],"ix":2,"l":2},"a":{"a":0,"k":[344.082,249.829,0],"ix":1,"l":2},"s":{"a":0,"k":[100,100,100],"ix":6,"l":2}},"ao":0,"ef":[{"ty":5,"nm":"Elastic Controller","np":5,"mn":"Pseudo/MDS Elastic Controller","ix":1,"en":1,"ef":[{"ty":0,"nm":"Amplitude","mn":"Pseudo/MDS Elastic Controller-0001","ix":1,"v":{"a":0,"k":27,"ix":1}},{"ty":0,"nm":"Frequency","mn":"Pseudo/MDS Elastic Controller-0002","ix":2,"v":{"a":0,"k":148,"ix":2}},{"ty":0,"nm":"Decay","mn":"Pseudo/MDS Elastic Controller-0003","ix":3,"v":{"a":0,"k":37,"ix":3}}]}],"shapes":[{"ty":"gr","it":[{"ind":0,"ty":"sh","ix":1,"ks":{"a":0,"k":{"i":[[-8.881,8.878],[0.888,-22.878],[3.88,-9.884],[41.844,-3.829],[0,0],[-4.436,52.423],[-9.097,67.291],[-1.644,32.858],[0.764,3.306],[0.89,0.81],[8.731,0.747],[25.829,3.311],[-2.635,19.018],[-6.876,2.584],[-13.226,-1.114],[-23.849,-43.415],[1.806,-19.512],[12.25,-100.798],[-25.398,-0.64],[0,0],[-9.197,21.173]],"o":[[16.419,-16.413],[-0.333,8.568],[-15.307,39.006],[0,0],[-52.752,-5.84],[10.313,-67.1],[4.504,-33.315],[0.17,-3.412],[-0.332,-1.439],[-6.718,-6.121],[-26.136,-2.238],[-17.358,-2.224],[1.014,-7.32],[10.351,-3.891],[44.417,3.739],[9.46,17.223],[-9.346,100.968],[0.288,24.491],[0,0],[22.144,-1.668],[5.871,-13.516]],"v":[[300.585,109.285],[342.943,129.799],[325.619,184.1],[235.085,249.579],[-159.138,249.577],[-240.566,147.542],[-210.051,-53.913],[-196.574,-160.522],[-197.004,-171.361],[-203.81,-183.03],[-234.038,-190.78],[-314.074,-195.936],[-341.196,-227.14],[-325.874,-245.689],[-264.824,-244.158],[-161.488,-198.665],[-151.528,-149.35],[-194.122,154.768],[-152.98,199.283],[227.906,199.293],[279.158,167.405]],"c":true},"ix":2},"nm":"Path 1","mn":"ADBE Vector Shape - Group","hd":false},{"ty":"fl","c":{"a":0,"k":[0.074509803922,0.258823529412,0.458823559331,1],"ix":4},"o":{"a":0,"k":100,"ix":5},"r":1,"bm":0,"nm":"Fill 1","mn":"ADBE Vector Graphic - Fill","hd":false},{"ty":"tr","p":{"a":0,"k":[344.081,249.829],"ix":2},"a":{"a":0,"k":[0,0],"ix":1},"s":{"a":0,"k":[100,100],"ix":3},"r":{"a":0,"k":0,"ix":6},"o":{"a":0,"k":100,"ix":7},"sk":{"a":0,"k":0,"ix":4},"sa":{"a":0,"k":0,"ix":5},"nm":"Transform"}],"nm":"Group 1","np":2,"cix":2,"bm":0,"ix":1,"mn":"ADBE Vector Group","hd":false}],"ip":6.00000024438501,"op":905.000036861406,"st":6.00000024438501,"bm":0},{"ddd":0,"ind":28,"ty":4,"nm":"Wheel right Outlines","sr":1,"ks":{"o":{"a":1,"k":[{"i":{"x":[0.833],"y":[0.833]},"o":{"x":[0.167],"y":[0.167]},"t":14,"s":[0]},{"t":17.0000006924242,"s":[100]}],"ix":11},"r":{"a":0,"k":0,"ix":10},"p":{"a":1,"k":[{"i":{"x":0,"y":1},"o":{"x":0.395,"y":0},"t":6,"s":[-378.657,1212.156,0],"to":[0,0,0],"ti":[0,0,0]},{"t":21.0000008553475,"s":[629.343,1212.156,0]}],"ix":2,"l":2},"a":{"a":0,"k":[51.75,51.75,0],"ix":1,"l":2},"s":{"a":0,"k":[100,100,100],"ix":6,"l":2}},"ao":0,"ef":[{"ty":5,"nm":"Elastic Controller","np":5,"mn":"Pseudo/MDS Elastic Controller","ix":1,"en":1,"ef":[{"ty":0,"nm":"Amplitude","mn":"Pseudo/MDS Elastic Controller-0001","ix":1,"v":{"a":0,"k":27,"ix":1}},{"ty":0,"nm":"Frequency","mn":"Pseudo/MDS Elastic Controller-0002","ix":2,"v":{"a":0,"k":148,"ix":2}},{"ty":0,"nm":"Decay","mn":"Pseudo/MDS Elastic Controller-0003","ix":3,"v":{"a":0,"k":37,"ix":3}}]}],"shapes":[{"ty":"gr","it":[{"ind":0,"ty":"sh","ix":1,"ks":{"a":0,"k":{"i":[[0,-28.442],[28.443,0],[0,28.442],[-28.442,0]],"o":[[0,28.442],[-28.442,0],[0,-28.442],[28.443,0]],"v":[[51.5,0],[0,51.5],[-51.5,0],[0,-51.5]],"c":true},"ix":2},"nm":"Path 1","mn":"ADBE Vector Shape - Group","hd":false},{"ty":"fl","c":{"a":0,"k":[0.074509803922,0.258823529412,0.458823559331,1],"ix":4},"o":{"a":0,"k":100,"ix":5},"r":1,"bm":0,"nm":"Fill 1","mn":"ADBE Vector Graphic - Fill","hd":false},{"ty":"tr","p":{"a":0,"k":[51.75,51.75],"ix":2},"a":{"a":0,"k":[0,0],"ix":1},"s":{"a":0,"k":[100,100],"ix":3},"r":{"a":0,"k":0,"ix":6},"o":{"a":0,"k":100,"ix":7},"sk":{"a":0,"k":0,"ix":4},"sa":{"a":0,"k":0,"ix":5},"nm":"Transform"}],"nm":"Group 1","np":2,"cix":2,"bm":0,"ix":1,"mn":"ADBE Vector Group","hd":false}],"ip":6.00000024438501,"op":905.000036861406,"st":6.00000024438501,"bm":0},{"ddd":0,"ind":30,"ty":4,"nm":"Wheel left Outlines","sr":1,"ks":{"o":{"a":1,"k":[{"i":{"x":[0.833],"y":[0.833]},"o":{"x":[0.167],"y":[0.167]},"t":14,"s":[0]},{"t":17.0000006924242,"s":[100]}],"ix":11},"r":{"a":0,"k":0,"ix":10},"p":{"a":1,"k":[{"i":{"x":0.667,"y":1},"o":{"x":0.395,"y":0},"t":6,"s":[-642.053,1212.324,0],"to":[0,0,0],"ti":[0,0,0]},{"t":21.0000008553475,"s":[365.947,1212.324,0]}],"ix":2,"l":2},"a":{"a":0,"k":[51.953,51.953,0],"ix":1,"l":2},"s":{"a":0,"k":[100,100,100],"ix":6,"l":2}},"ao":0,"ef":[{"ty":5,"nm":"Elastic Controller","np":5,"mn":"Pseudo/MDS Elastic Controller","ix":1,"en":1,"ef":[{"ty":0,"nm":"Amplitude","mn":"Pseudo/MDS Elastic Controller-0001","ix":1,"v":{"a":0,"k":27,"ix":1}},{"ty":0,"nm":"Frequency","mn":"Pseudo/MDS Elastic Controller-0002","ix":2,"v":{"a":0,"k":148,"ix":2}},{"ty":0,"nm":"Decay","mn":"Pseudo/MDS Elastic Controller-0003","ix":3,"v":{"a":0,"k":37,"ix":3}}]}],"shapes":[{"ty":"gr","it":[{"ind":0,"ty":"sh","ix":1,"ks":{"a":0,"k":{"i":[[0,-28.555],[28.555,0],[0,28.555],[-28.555,0]],"o":[[0,28.555],[-28.555,0],[0,-28.555],[28.555,0]],"v":[[51.703,0],[0,51.703],[-51.703,0],[0,-51.703]],"c":true},"ix":2},"nm":"Path 1","mn":"ADBE Vector Shape - Group","hd":false},{"ty":"fl","c":{"a":0,"k":[0.074509803922,0.258823529412,0.458823559331,1],"ix":4},"o":{"a":0,"k":100,"ix":5},"r":1,"bm":0,"nm":"Fill 1","mn":"ADBE Vector Graphic - Fill","hd":false},{"ty":"tr","p":{"a":0,"k":[51.953,51.953],"ix":2},"a":{"a":0,"k":[0,0],"ix":1},"s":{"a":0,"k":[100,100],"ix":3},"r":{"a":0,"k":0,"ix":6},"o":{"a":0,"k":100,"ix":7},"sk":{"a":0,"k":0,"ix":4},"sa":{"a":0,"k":0,"ix":5},"nm":"Transform"}],"nm":"Group 1","np":2,"cix":2,"bm":0,"ix":1,"mn":"ADBE Vector Group","hd":false}],"ip":6.00000024438501,"op":905.000036861406,"st":6.00000024438501,"bm":0}],"markers":[]}